neuralspace/__init__.py
neuralspace/cli.py
neuralspace/constants.py
neuralspace/env.py
neuralspace/utils.py
neuralspace/version.py
neuralspace/voice_ai.py
neuralspace-1.2.0.dist-info/METADATA
neuralspace-1.2.0.dist-info/WHEEL
neuralspace-1.2.0.dist-info/entry_points.txt
neuralspace-1.2.0.dist-info/top_level.txt
neuralspace-1.2.0.dist-info/RECORD
