Metadata-Version: 2.1
Name: neuralspace
Version: 1.2.0
Home-page: https://voice.neuralspace.ai
Project-URL: Docs, https://voice.neuralspace.ai/docs
Project-URL: Source, https://github.com/Neural-Space/neuralspace-python
Classifier: Programming Language :: Python :: 3
Requires-Python: >=3.7
Requires-Dist: requests
Requires-Dist: websocket_client
Requires-Dist: typer
